<?xml version="1.0" encoding="UTF-8"?>
<menu id="root_timeline">
  <meta>
    <select id="today" /> 
    <action module="ActionTimeline"  menu="xml/ActionHints.xml" />
    <screen>
      <element id="container" type="Container" x="470" y="50" width="710" height="410" />
      <element id="txtHolder" type="TextField" x="20" y="20" width="370" height="380" />
      <element id="imgHolder" type="MovieClip" x="410" y="0"/>
      <element id="progHolder" type="MovieClip" x="20" y="320"/>
    </screen>
  </meta>
  <item id="7+ days" title="7+ days">
    <icon url="media/icons/submenu/submenu icon suggestions 7+ days.png" />
    <item id="dexter" text="Dexter">
      <meta>
        <duration>60</duration>
      </meta>
      <info url="media/tv/dexter.png">
        <percent val="0"/>
        <prog id="mad"/>
        <shorttext>
          <span class="headline">Dexter</span>
          <p class="subheadline">Dark Comedy, USA 2008</p>
          <p class="subsubheadline">Season 2, Ep. 11: Left Turn Ahead</p>
          <p class="description">Dexter begins to put his affairs in order as he prepares to make a potentially life-altering decision. Doakes runs afoul of drug smugglers during a daring escape. Angel faces criminal charges. Lundy deals with his FBI superior. Lila comes across one of Dexter's dangerous secrets.</p>
        </shorttext>
        <time><start hour="20" min="20"/><end hour="21" min="20"/></time></info>
    </item>
    <item id="dawsons-creek" text="Dawson's Creek">
      <meta>
        <duration>60</duration>
      </meta>
      <info url="media/tv/dawsons-creek.png">
        <percent val="0"/>
        <prog id="Euro Sport"/>
        <shorttext>
          <span class="headline">Dawson's Creek</span>
          <p class="subheadline">Soap Opera, USA 2003</p>
          <p class="subsubheadline">Season 6, Ep. 19: Lovelines</p>
          <p class="description">Joey and Eddie's emotional and sexual relationship is played out on stage during a counseling center benefit. At the same event, Jack and David deal with the insecurities in their relationship, Jen opens up to C.J. about Grams' cancer, and a sober Audrey returns to Boston and surprises everyone at the benefit.</p>
        </shorttext>
        <time><start hour="21" min="20"/><end hour="22" min="20"/></time></info>
    </item>
    <item id="ugly-betty" text="Ugly Betty">
      <meta>
        <duration>60</duration>
      </meta>
      <info url="media/tv/ugly-betty.png">
        <percent val="0"/>
        <prog id="Nova TV"/>
        <shorttext>
          <span class="headline">Ugly Betty</span>
          <p class="subheadline">Comedy, USA 2008</p>
          <p class="subsubheadline">Season 2, Ep. 18: Jump</p>
          <p class="description">A teenager arrives who may be Meade-related. Also Henry comes back to propose to Betty, as well as Gio asking her to go to Rome with him for a holiday. Wilhelmina takes over Daniel as editor-in-chief. Lindsay Lohan is set to play an old schoolmate of Betty's.</p>
        </shorttext>
        <time><start hour="22" min="20"/><end hour="23" min="20"/></time></info>
    </item>
  </item>
  <item id="2-7 days" title="2-7 days">
    <icon url="media/icons/submenu/submenu icon suggestions 2-7 days.png" />
    <item id="csi-miami" text="CSI: Miami">
      <meta>
        <duration>70</duration>
      </meta>
      <info url="media/tv/csi-miami.png">
        <percent val="0"/>
        <prog id="euronews"/>
        <shorttext>
          <span class="headline">CSI: Miami</span>
          <p class="subheadline">Crime Drama, USA 2008</p>
          <p class="subsubheadline">Season 6, Ep. 18: Tunnel Vision</p>
          <p class="description">The episode opens with two men chasing each other on the causeway. When the road collapses one man is thrown into a sinkhole and killed. While investigating, the CSIs discover a conspiracy to rob a bank.</p>
        </shorttext>
        <time><start hour="17" min="40"/><end hour="18" min="50"/></time></info>
    </item>
    <item id="rome" text="Rome">
      <meta>
        <duration>90</duration>
      </meta>
      <info url="media/tv/rome.png">
        <percent val="0"/>
        <prog id="Sky One"/>
        <shorttext>
          <span class="headline">Rome</span>
          <p class="subheadline">Drama, UK/USA 2007</p>
          <p class="subsubheadline">Season 2, Ep. 7: Death Mask</p>
          <p class="description">Servilia mourns the death of Brutus, killed at Phillipi. She kneels in front of Atia's door chanting repeatedly for justice. Although Atia ignores her initially, the incessant chanting attracts a crowd of pleb onlookers and annoys Atia.</p>
        </shorttext>
        <time><start hour="18" min="50"/><end hour="20" min="20"/></time></info>
    </item>
    <item id="oceans-eleven" text="Ocean's Eleven">
      <meta>
        <duration>120</duration>
      </meta>
      <info url="media/tv/oceans-eleven.png">
        <percent val="0"/>
        <prog id="cnn"/>
        <shorttext>
          <span class="headline">Ocean's Eleven</span>
          <p class="subheadline">Crime Dramedy, USA 2001</p>
          <p class="description">Danny Ocean wants to score the biggest heist in history. He combines an eleven team member, including Frank Catton, Rusty Ryan and Linus Caldwell. Their target? The Bellagio, the Mirage and the MGM Grand, all casinos owned by Terry Benedict. It's not going to be easy, as they plan to get in secretly and out with $150 million.</p>
        </shorttext>
        <time><start hour="09" min="20"/><end hour="11" min="20"/></time></info>
    </item>
    <item id="lost" text="Lost">
      <meta>
        <duration>60</duration>
      </meta>
      <info url="media/tv/lost.png">
        <percent val="0"/>
        <prog id="rtl2"/>
        <shorttext>
          <span class="headline">Lost</span>
          <p class="subheadline">Drama, USA 2008</p>
          <p class="subsubheadline">Season 4, Ep. 6: The Other Woman</p>
          <p class="description">Juliet and Jack pursue Daniel and Charlotte, after they leave without notice for the Dharma electrical station, where they render a deadly gas inert. Meanwhile, Ben tells Locke about Widmore. Flashbacks show Juliet's relationships with Ben, her lover Goodwin and his wife Harper.</p>
        </shorttext>
        <time><start hour="11" min="20"/><end hour="12" min="20"/></time></info>
    </item>
    <item id="six-feet-under" text="Six Feet Under">
      <meta>
        <duration>90</duration>
      </meta>
      <info url="media/tv/six-feet-under.png">
        <percent val="0"/>
        <prog id="Kabel1"/>
        <shorttext>
          <span class="headline">Six Feet Under</span>
          <p class="subheadline">Drama, USA 2005</p>
          <p class="subsubheadline">Season 5, Ep. 9: Ecotone</p>
          <p class="description">After suffering a massive seizure, Nate is taken to the hospital. As Nate undergoes surgery, tension ensues between Maggie and Brenda in the waiting room. Elsewhere, Ruth is still camping in the wildnerness with Hiram and is completely oblivious to what is happening with her family in L.A.</p>
        </shorttext>
        <time><start hour="12" min="20"/><end hour="13" min="50"/></time></info>
    </item>
    <item id="21-grams" text="21 Grams">
      <meta>
        <duration>120</duration>
      </meta>
      <info url="media/tv/21-grams.png">
        <percent val="0"/>
        <prog id="sf1"/>
        <shorttext>
          <span class="headline">21 Grams</span>
          <p class="subheadline">Drama, USA 2003</p>
          <p class="description">This is the story of three gentle persons: Paul Rivers an ailing mathematician lovelessly married to an English emigree, Christina Peck, an upper-middle-class suburban housewife, happily married and mother of two little girls, and Jack Jordan, an ex-convict who has found in his Christian faith the strength to raise a family.</p>
        </shorttext>
        <time><start hour="13" min="50"/><end hour="15" min="50"/></time></info>
    </item>
    <item id="burn-notice" text="Burn Notice">
      <meta>
        <duration>50</duration>
      </meta>
      <info url="media/tv/burn-notice.png">
        <percent val="0"/>
        <prog id="BBC HD"/>
        <shorttext>
          <span class="headline">Burn Notice</span>
          <p class="subheadline">Dramedy, USA 2008</p>
          <p class="subsubheadline">Season 1, Ep. 3: Fight or Flight</p>
          <p class="description">A woman who witnessed a brutal beating receives threats from the drug dealer who carried out the crime. Michael tries to get her out of Miami to safety, but the woman's teenage daughter refuses to leave the city, forcing him to try a risky plan to alienate the dealer from his cartel.</p>
        </shorttext>
        <time><start hour="15" min="50"/><end hour="16" min="40"/></time></info>
    </item>
    <item id="tudors" text="The Tudors">
      <meta>
        <duration>60</duration>
      </meta>
      <info url="media/tv/tudors.png">
        <percent val="0"/>
        <prog id="orf2"/>
        <shorttext>
          <span class="headline">The Tudors</span>
          <p class="subheadline">Historical Drama, UK 2008</p>
          <p class="subsubheadline">Season 2, Ep. 9: Kings Aside</p>
          <p class="description">Anne has lost a son and with it her last chance at a lasting marriage with Henry. The King's affections are shifting anyway: the Seymour family are awarded rooms at court and seem likely to replace the Boleyns as royal favourites. Several in the court begin to move against Anne who is accused of adultery.</p>
        </shorttext>
        <time><start hour="16" min="40"/><end hour="17" min="40"/></time></info>
    </item>
  </item>
  <item id="tomorrow" title="Tomorrow">
    <icon url="media/icons/submenu/submenu icon suggestions tomorrow.png" />
    <item id="dr-who" text="Dr. Who">
      <meta>
        <duration>60</duration>
      </meta>
      <info url="media/tv/dr-who.png">
        <percent val="0"/>
        <prog id="premiere"/>
        <shorttext>
          <span class="headline">Dr. Who</span>
          <p class="subheadline">Sci-Fi, UK 2008</p>
          <p class="subsubheadline">Season 4, Ep. 10: Midnight</p>
          <p class="description">The Doctor and Donna take a holiday on the crystalline planet Midnight, which orbits close enough to its sun that the Xtonic radiation exposure would vaporise any living thing walking unprotected on its surface.</p>
        </shorttext>
        <time><start hour="21" min="00"/><end hour="22" min="00"/></time></info>
    </item>
    <item id="six-feet-under" text="Six Feet Under">
      <meta>
        <duration>90</duration>
      </meta>
      <info url="media/tv/six-feet-under.png">
        <percent val="0"/>
        <prog id="orf1"/>
        <shorttext>
          <span class="headline">Six Feet Under</span>
          <p class="subheadline">Drama, USA 2005</p>
          <p class="subsubheadline">Season 5, Ep. 9: Ecotone</p>
          <p class="description">After suffering a massive seizure, Nate is taken to the hospital. As Nate undergoes surgery, tension ensues between Maggie and Brenda in the waiting room. Elsewhere, Ruth is still camping in the wildnerness with Hiram and is completely oblivious to what is happening with her family in L.A.</p>
        </shorttext>
        <time><start hour="22" min="00"/><end hour="23" min="30"/></time></info>
    </item>
  </item>
  <item id="today" title="Today">
    <icon url="media/icons/submenu/submenu icon suggestions today.png" />
    <item id="american-beauty" text="American Beauty">
      <meta>
        <duration>120</duration>
      </meta>
      <info url="media/tv/american-beauty.png">
        <percent val="0"/>
        <prog id="sat1"/>
        <shorttext>
          <span class="headline">American Beauty</span>
          <p class="subheadline">Drama, USA 1999</p>
          <p class="description">Lester Burnham, a man in his mid-40s going through an intense midlife crisis, has grown cynical and is convinced that he has no reason to go on. After developing an infatuation for his daughter's attractive friend, he decides to turn his hectic life around.</p>
        </shorttext>
        <time><start hour="18" min="00"/><end hour="20" min="00"/></time></info>
    </item>
    <item id="dirt" text="Dirt">
      <meta>
        <duration>60</duration>
      </meta>
      <info url="media/tv/dirt.png">
        <percent val="0"/>
        <prog id="pro7"/>
        <shorttext>
          <span class="headline">Dirt</span>
          <p class="subheadline">Drama, USA 2007</p>
          <p class="subsubheadline">Season 2, Ep. 1: Welcome to Normal</p>
          <p class="description">After surviving her violent attack, Lucy Spiller returns to Dirt Now magazine to reclaim her position as Tabloid Queen. Julia, while fleeing the scene, is hit by Leo and eventually gets killed. A chance encounter between Lucy and a young pop star results in a surprising opportunity.</p>
        </shorttext>
        <time><start hour="20" min="00"/><end hour="21" min="00"/></time></info>
    </item>
  </item>
</menu>
